liberty.py
liberty_secrets-1.1.0.dist-info/licenses/LICENSE
liberty_secrets-1.1.0.dist-info/METADATA
liberty_secrets-1.1.0.dist-info/WHEEL
liberty_secrets-1.1.0.dist-info/entry_points.txt
liberty_secrets-1.1.0.dist-info/top_level.txt
liberty_secrets-1.1.0.dist-info/RECORD
